[{
  "gamerTag": "kestern88",
  "xboxdata": {
    "freshness": "new",
    "recentactivity": null,
    "biography": "",
    "location": "Tyler, TX",
    "name": "",
    "motto": "",
    "online": false,
    "presence": "Last seen 22 hours ago playing Xbox One",
    "reputation": 20,
    "gamerscore": 3495,
    "avatar": {
      "tile": "http://avatar.xboxlive.com/avatar/kestern88/avatarpic-l.png",
      "large": "http://avatar.xboxlive.com/avatar/kestern88/avatarpic-l.png",
      "small": "http://avatar.xboxlive.com/avatar/kestern88/avatarpic-s.png",
      "full": "http://avatar.xboxlive.com/avatar/kestern88/avatar-body.png"
    },
    "badges": {
      "kinectlaunchteam": false,
      "nxelaunchteam": false,
      "xboxlaunchteam": false
    },
    "tier": "gold",
    "gamertag": "kestern88"
  },
  "games": ["Battlefield 4", "Call of Duty: Ghosts"]
},
{
  "gamerTag": "alice01",
  "xboxdata": {
    "freshness": "new",
    "recentactivity": null,
    "biography": "",
    "location": "San Francisco, CA",
    "name": "",
    "motto": "",
    "online": false,
    "presence": "Last seen 22 hours ago playing Xbox One",
    "reputation": 9,
    "gamerscore": 3495,
    "avatar": {
      "tile": "http://avatar.xboxlive.com/avatar/kestern88/avatarpic-l.png",
      "large": "http://avatar.xboxlive.com/avatar/kestern88/avatarpic-l.png",
      "small": "http://avatar.xboxlive.com/avatar/kestern88/avatarpic-s.png",
      "full": "http://avatar.xboxlive.com/avatar/kestern88/avatar-body.png"
    },
    "badges": {
      "kinectlaunchteam": false,
      "nxelaunchteam": false,
      "xboxlaunchteam": false
    },
    "tier": "gold",
    "gamertag": "alice01"
  },
  "games": ["Battlefield 4", "Call of Duty: Ghosts", "Need For Speed", "Titanfall"]
},
{
  "gamerTag": "bob02",
  "xboxdata": {
    "freshness": "new",
    "recentactivity": null,
    "biography": "",
    "location": "Ny, NY",
    "name": "",
    "motto": "",
    "online": false,
    "presence": "Last seen 22 hours ago playing Xbox One",
    "reputation": 9,
    "gamerscore": 3495,
    "avatar": {
      "tile": "http://avatar.xboxlive.com/avatar/kestern88/avatarpic-l.png",
      "large": "http://avatar.xboxlive.com/avatar/kestern88/avatarpic-l.png",
      "small": "http://avatar.xboxlive.com/avatar/kestern88/avatarpic-s.png",
      "full": "http://avatar.xboxlive.com/avatar/kestern88/avatar-body.png"
    },
    "badges": {
      "kinectlaunchteam": false,
      "nxelaunchteam": false,
      "xboxlaunchteam": false
    },
    "tier": "gold",
    "gamertag": "bob02"
  },
  "games": ["Battlefield 4", "Call of Duty: Ghosts", "Need For Speed"]
},
{
  "gamerTag": "charlie03",
  "xboxdata": {
    "freshness": "new",
    "recentactivity": null,
    "biography": "",
    "location": "Ny, NY",
    "name": "",
    "motto": "",
    "online": false,
    "presence": "Last seen 22 hours ago playing Xbox One",
    "reputation": 9,
    "gamerscore": 3495,
    "avatar": {
      "tile": "http://avatar.xboxlive.com/avatar/kestern88/avatarpic-l.png",
      "large": "http://avatar.xboxlive.com/avatar/kestern88/avatarpic-l.png",
      "small": "http://avatar.xboxlive.com/avatar/kestern88/avatarpic-s.png",
      "full": "http://avatar.xboxlive.com/avatar/kestern88/avatar-body.png"
    },
    "badges": {
      "kinectlaunchteam": false,
      "nxelaunchteam": false,
      "xboxlaunchteam": false
    },
    "tier": "gold",
    "gamertag": "charlie03"
  },
  "games": ["Battlefield 4", "Call of Duty: Ghosts", "Titanfall"]
},
{
  "gamerTag": "danielle04",
  "xboxdata": {
    "freshness": "new",
    "recentactivity": null,
    "biography": "",
    "location": "Houston, TX",
    "name": "",
    "motto": "",
    "online": false,
    "presence": "Last seen 22 hours ago playing Xbox One",
    "reputation": 9,
    "gamerscore": 3495,
    "avatar": {
      "tile": "http://avatar.xboxlive.com/avatar/kestern88/avatarpic-l.png",
      "large": "http://avatar.xboxlive.com/avatar/kestern88/avatarpic-l.png",
      "small": "http://avatar.xboxlive.com/avatar/kestern88/avatarpic-s.png",
      "full": "http://avatar.xboxlive.com/avatar/kestern88/avatar-body.png"
    },
    "badges": {
      "kinectlaunchteam": false,
      "nxelaunchteam": false,
      "xboxlaunchteam": false
    },
    "tier": "gold",
    "gamertag": "danielle04"
  },
  "games": ["Battlefield 4"]
},
{
  "gamerTag": "elen05",
  "xboxdata": {
    "freshness": "new",
    "recentactivity": null,
    "biography": "",
    "location": "Miami, FL",
    "name": "",
    "motto": "",
    "online": false,
    "presence": "Last seen 22 hours ago playing Xbox One",
    "reputation": 9,
    "gamerscore": 3495,
    "avatar": {
      "tile": "http://avatar.xboxlive.com/avatar/kestern88/avatarpic-l.png",
      "large": "http://avatar.xboxlive.com/avatar/kestern88/avatarpic-l.png",
      "small": "http://avatar.xboxlive.com/avatar/kestern88/avatarpic-s.png",
      "full": "http://avatar.xboxlive.com/avatar/kestern88/avatar-body.png"
    },
    "badges": {
      "kinectlaunchteam": false,
      "nxelaunchteam": false,
      "xboxlaunchteam": false
    },
    "tier": "gold",
    "gamertag": "elen05"    
  },
  "games": ["Need For Speed"]
},
{
  "gamerTag": "frank06",
  "xboxdata": {
    "freshness": "new",
    "recentactivity": null,
    "biography": "",
    "location": "Portland, OR",
    "name": "",
    "motto": "",
    "online": false,
    "presence": "Last seen 22 hours ago playing Xbox One",
    "reputation": 9,
    "gamerscore": 3495,
    "avatar": {
      "tile": "http://avatar.xboxlive.com/avatar/kestern88/avatarpic-l.png",
      "large": "http://avatar.xboxlive.com/avatar/kestern88/avatarpic-l.png",
      "small": "http://avatar.xboxlive.com/avatar/kestern88/avatarpic-s.png",
      "full": "http://avatar.xboxlive.com/avatar/kestern88/avatar-body.png"
    },
    "badges": {
      "kinectlaunchteam": false,
      "nxelaunchteam": false,
      "xboxlaunchteam": false
    },
    "tier": "gold",
    "gamertag": "frank06"
  },
  "games": ["Battlefield 4", "Titanfall"]
}]